yasp/__init__.py
yasp-0.1.1.dist-info/LICENSE
yasp-0.1.1.dist-info/METADATA
yasp-0.1.1.dist-info/WHEEL
yasp-0.1.1.dist-info/top_level.txt
yasp-0.1.1.dist-info/RECORD
