Metadata-Version: 2.1
Name: yasp
Version: 0.1.1
Summary: Yet another Apertium stream parser
Author-email: Vee Satayamas <vsatayamas@gmail.com>
Project-URL: homepage, https://git.sr.ht/~veer66/yasp
Keywords: apertium,stream,parser
Classifier: Programming Language :: Python :: 3
Classifier: License :: OSI Approved :: GNU General Public License v3 (GPLv3)
Classifier: Intended Audience :: Developers
Classifier: Operating System :: OS Independent
Classifier: Topic :: Software Development :: Libraries
License-File: LICENSE
Requires-Dist: parsec (==3.14)
